itkwasm/__init__.py
itkwasm/binary_file.py
itkwasm/binary_stream.py
itkwasm/cast_image.py
itkwasm/environment_dispatch.py
itkwasm/float_types.py
itkwasm/image.py
itkwasm/image_from_array.py
itkwasm/int_types.py
itkwasm/interface_types.py
itkwasm/json_compatible.py
itkwasm/mesh.py
itkwasm/pipeline.py
itkwasm/pipeline_input.py
itkwasm/pipeline_output.py
itkwasm/pixel_types.py
itkwasm/point_set.py
itkwasm/polydata.py
itkwasm/pyodide.py
itkwasm/text_file.py
itkwasm/text_stream.py
itkwasm/to_cupy_array.py
itkwasm/to_numpy_array.py
itkwasm/transform.py
itkwasm/transform_parameterizations.py
itkwasm-1.0b195.dist-info/METADATA
itkwasm-1.0b195.dist-info/WHEEL
itkwasm-1.0b195.dist-info/licenses/LICENSE
itkwasm-1.0b195.dist-info/RECORD
