Metadata-Version: 2.3
Name: itkwasm
Version: 1.0b195
Summary: Python interface to itk-wasm WebAssembly (Wasm) modules.
Project-URL: Home, https://itkwasm.readthedocs.io
Project-URL: Source, https://github.com/InsightSoftwareConsortium/ITK-Wasm
Project-URL: Issues, https://github.com/InsightSoftwareConsortium/ITK-Wasm/issues
Author-email: Matt McCormick <matt@fideus.io>
License: 
License-File: LICENSE
Keywords: imaging,itk,visualization
Classifier: Development Status :: 4 - Beta
Classifier: Intended Audience :: Developers
Classifier: Intended Audience :: Science/Research
Classifier: License :: OSI Approved :: Apache Software License
Classifier: Programming Language :: Python
Classifier: Programming Language :: Python :: 3
Classifier: Programming Language :: Python :: 3.9
Classifier: Programming Language :: Python :: 3.10
Classifier: Programming Language :: Python :: 3.11
Classifier: Programming Language :: Python :: 3.12
Classifier: Programming Language :: Python :: 3.13
Requires-Python: >=3.9
Requires-Dist: importlib-metadata; python_version < '3.10'
Requires-Dist: numpy
Requires-Dist: platformdirs; sys_platform != 'emscripten'
Requires-Dist: typing-extensions
Requires-Dist: wasmtime>=28.0.0; sys_platform != 'emscripten'
